{
  "color-primary-100": "#D6E4FF",
  "color-primary-200": "#ADC8FF",
  "color-primary-300": "#84A9FF",
  "color-primary-400": "#6690FF",
  "color-primary-500": "#3366FF",
  "color-primary-600": "#254EDB",
  "color-primary-700": "#1939B7",
  "color-primary-800": "#102693",
  "color-primary-900": "#091A7A",
  "color-primary-transparent-100": "rgba(51, 102, 255, 0.08)",
  "color-primary-transparent-200": "rgba(51, 102, 255, 0.16)",
  "color-primary-transparent-300": "rgba(51, 102, 255, 0.24)",
  "color-primary-transparent-400": "rgba(51, 102, 255, 0.32)",
  "color-primary-transparent-500": "rgba(51, 102, 255, 0.4)",
  "color-primary-transparent-600": "rgba(51, 102, 255, 0.48)",
  "color-success-100": "#F4F6EF",
  "color-success-200": "#EAEDE0",
  "color-success-300": "#C5C9B9",
  "color-success-400": "#8F9385",
  "color-success-500": "#494c42",
  "color-success-600": "#3B4130",
  "color-success-700": "#2E3621",
  "color-success-800": "#232C15",
  "color-success-900": "#1A240C",
  "color-success-transparent-100": "rgba(73, 76, 66, 0.08)",
  "color-success-transparent-200": "rgba(73, 76, 66, 0.16)",
  "color-success-transparent-300": "rgba(73, 76, 66, 0.24)",
  "color-success-transparent-400": "rgba(73, 76, 66, 0.32)",
  "color-success-transparent-500": "rgba(73, 76, 66, 0.4)",
  "color-success-transparent-600": "rgba(73, 76, 66, 0.48)",
  "color-info-100": "#D8FFFD",
  "color-info-200": "#B2FBFF",
  "color-info-300": "#8CF2FF",
  "color-info-400": "#6FE5FF",
  "color-info-500": "#40cfff",
  "color-info-600": "#2EA3DB",
  "color-info-700": "#207CB7",
  "color-info-800": "#145893",
  "color-info-900": "#0C3F7A",
  "color-info-transparent-100": "rgba(64, 207, 255, 0.08)",
  "color-info-transparent-200": "rgba(64, 207, 255, 0.16)",
  "color-info-transparent-300": "rgba(64, 207, 255, 0.24)",
  "color-info-transparent-400": "rgba(64, 207, 255, 0.32)",
  "color-info-transparent-500": "rgba(64, 207, 255, 0.4)",
  "color-info-transparent-600": "rgba(64, 207, 255, 0.48)",
  "color-warning-100": "#FFF6D9",
  "color-warning-200": "#FFEAB3",
  "color-warning-300": "#FFDC8D",
  "color-warning-400": "#FFCD71",
  "color-warning-500": "#FFB642",
  "color-warning-600": "#DB9230",
  "color-warning-700": "#B77121",
  "color-warning-800": "#935315",
  "color-warning-900": "#7A3E0C",
  "color-warning-transparent-100": "rgba(255, 182, 66, 0.08)",
  "color-warning-transparent-200": "rgba(255, 182, 66, 0.16)",
  "color-warning-transparent-300": "rgba(255, 182, 66, 0.24)",
  "color-warning-transparent-400": "rgba(255, 182, 66, 0.32)",
  "color-warning-transparent-500": "rgba(255, 182, 66, 0.4)",
  "color-warning-transparent-600": "rgba(255, 182, 66, 0.48)",
  "color-danger-100": "#FFE5D4",
  "color-danger-200": "#FFC5AA",
  "color-danger-300": "#FF9E7F",
  "color-danger-400": "#FF7960",
  "color-danger-500": "#FF3C2B",
  "color-danger-600": "#DB1F1F",
  "color-danger-700": "#B71523",
  "color-danger-800": "#930D24",
  "color-danger-900": "#7A0824",
  "color-danger-transparent-100": "rgba(255, 60, 43, 0.08)",
  "color-danger-transparent-200": "rgba(255, 60, 43, 0.16)",
  "color-danger-transparent-300": "rgba(255, 60, 43, 0.24)",
  "color-danger-transparent-400": "rgba(255, 60, 43, 0.32)",
  "color-danger-transparent-500": "rgba(255, 60, 43, 0.4)",
  "color-danger-transparent-600": "rgba(255, 60, 43, 0.48)"
}